{
  "day": 21,
  "words": [
    {
      "word": "taken",
      "en": "The data reveal a strong correlation between carbon emissions and taken.",
      "tr": "alınmış",
      "synonyms": "",
      "type": "noun",
      "en_tr": "Veriler, karbon emisyonları ile alınmış arasında güçlü bir korelasyon olduğunu ortaya koyuyor.",
      "collocation": "crucial taken, study of taken",
      "sentences": [
        {
          "en": "The data reveal a strong correlation between carbon emissions and taken.",
          "tr": "Veriler, karbon emisyonları ile alınmış arasında güçlü bir korelasyon olduğunu ortaya koyuyor.",
          "blanked": "The data reveal a strong correlation between carbon emissions and ________."
        },
        {
          "en": "Recent studies have demonstrated the significant impact of taken on the ecosystem.",
          "tr": "Son çalışmalar, alınmış yapısının ekosistem üzerindeki önemli etkisini göstermiştir.",
          "blanked": "Recent studies have demonstrated the significant impact of ________ on the ecosystem."
        },
        {
          "en": "Researchers must carefully monitor the changes in taken during the experiment.",
          "tr": "Araştırmacılar, deney sırasında alınmış durumundaki değişimleri dikkatle gözlemlemelidir.",
          "blanked": "Researchers must carefully monitor the changes in ________ during the experiment."
        },
        {
          "en": "A key factor in achieving sustainable development is controlling the level of taken.",
          "tr": "Sürdürülebilir kalkınmayı sağlamada temel faktör, alınmış seviyesinin kontrol edilmesidir.",
          "blanked": "A key factor in achieving sustainable development is controlling the level of ________."
        },
        {
          "en": "The primary objective of this project is to analyze the behavior of taken under pressure.",
          "tr": "Bu projenin temel amacı, basınç altında alınmış davranışını analiz etmektir.",
          "blanked": "The primary objective of this project is to analyze the behavior of ________ under pressure."
        }
      ],
      "priority": "Çok Yüksek Sıklık"
    },
    {
      "word": "sleep",
      "en": "The data reveal a strong correlation between carbon emissions and sleep.",
      "tr": "uyku",
      "synonyms": "",
      "type": "noun",
      "en_tr": "Veriler, karbon emisyonları ile uyku arasında güçlü bir korelasyon olduğunu ortaya koyuyor.",
      "collocation": "crucial sleep, study of sleep",
      "sentences": [
        {
          "en": "The data reveal a strong correlation between carbon emissions and sleep.",
          "tr": "Veriler, karbon emisyonları ile uyku arasında güçlü bir korelasyon olduğunu ortaya koyuyor.",
          "blanked": "The data reveal a strong correlation between carbon emissions and ________."
        },
        {
          "en": "Recent studies have demonstrated the significant impact of sleep on the ecosystem.",
          "tr": "Son çalışmalar, uyku yapısının ekosistem üzerindeki önemli etkisini göstermiştir.",
          "blanked": "Recent studies have demonstrated the significant impact of ________ on the ecosystem."
        },
        {
          "en": "Researchers must carefully monitor the changes in sleep during the experiment.",
          "tr": "Araştırmacılar, deney sırasında uyku durumundaki değişimleri dikkatle gözlemlemelidir.",
          "blanked": "Researchers must carefully monitor the changes in ________ during the experiment."
        },
        {
          "en": "A key factor in achieving sustainable development is controlling the level of sleep.",
          "tr": "Sürdürülebilir kalkınmayı sağlamada temel faktör, uyku seviyesinin kontrol edilmesidir.",
          "blanked": "A key factor in achieving sustainable development is controlling the level of ________."
        },
        {
          "en": "The primary objective of this project is to analyze the behavior of sleep under pressure.",
          "tr": "Bu projenin temel amacı, basınç altında uyku davranışını analiz etmektir.",
          "blanked": "The primary objective of this project is to analyze the behavior of ________ under pressure."
        }
      ],
      "priority": "Çok Yüksek Sıklık"
    },
    {
      "word": "ensure",
      "en": "It is essential to ensure the system properties to get accurate results.",
      "tr": "garantiye almak, emin olmak",
      "synonyms": "",
      "type": "noun",
      "en_tr": "Doğru sonuçlar elde etmek için sistem özelliklerini garantiye almak, emin olmak gereklidir.",
      "collocation": "crucial ensure, study of ensure",
      "sentences": [
        {
          "en": "It is essential to ensure the system properties to get accurate results.",
          "tr": "Doğru sonuçlar elde etmek için sistem özelliklerini garantiye almak, emin olmak gereklidir.",
          "blanked": "It is essential to ________ the system properties to get accurate results."
        },
        {
          "en": "Researchers always seek to ensure new methodologies in this field.",
          "tr": "Araştırmacılar bu alanda her zaman yeni metodolojiler garantiye almak, emin olmak isterler.",
          "blanked": "Researchers always seek to ________ new methodologies in this field."
        },
        {
          "en": "We need to ensure the main factors before drawing a final conclusion.",
          "tr": "Nihai bir sonuca varmadan önce ana faktörleri garantiye almak, emin olmak gerekir.",
          "blanked": "We need to ________ the main factors before drawing a final conclusion."
        },
        {
          "en": "Several parameters were designed to ensure the chemical reaction.",
          "tr": "Kimyasal reaksiyonu garantiye almak, emin olmak için birkaç parametre tasarlandı.",
          "blanked": "Several parameters were designed to ________ the chemical reaction."
        },
        {
          "en": "The new algorithm can ensure the overall processing speed.",
          "tr": "Yeni algoritma, genel işlem hızını garantiye almak, emin olmak konusunda yardımcı olabilir.",
          "blanked": "The new algorithm can ________ the overall processing speed."
        }
      ],
      "priority": "Çok Yüksek Sıklık"
    },
    {
      "word": "wouldhavemoved",
      "en": "The data reveal a strong correlation between carbon emissions and wouldhavemoved.",
      "tr": "hareket etmiş olacaktı",
      "synonyms": "",
      "type": "noun",
      "en_tr": "Veriler, karbon emisyonları ile hareket etmiş olacaktı arasında güçlü bir korelasyon olduğunu ortaya koyuyor.",
      "collocation": "crucial wouldhavemoved, study of wouldhavemoved",
      "sentences": [
        {
          "en": "The data reveal a strong correlation between carbon emissions and wouldhavemoved.",
          "tr": "Veriler, karbon emisyonları ile hareket etmiş olacaktı arasında güçlü bir korelasyon olduğunu ortaya koyuyor.",
          "blanked": "The data reveal a strong correlation between carbon emissions and ________."
        },
        {
          "en": "Recent studies have demonstrated the significant impact of wouldhavemoved on the ecosystem.",
          "tr": "Son çalışmalar, hareket etmiş olacaktı yapısının ekosistem üzerindeki önemli etkisini göstermiştir.",
          "blanked": "Recent studies have demonstrated the significant impact of ________ on the ecosystem."
        },
        {
          "en": "Researchers must carefully monitor the changes in wouldhavemoved during the experiment.",
          "tr": "Araştırmacılar, deney sırasında hareket etmiş olacaktı durumundaki değişimleri dikkatle gözlemlemelidir.",
          "blanked": "Researchers must carefully monitor the changes in ________ during the experiment."
        },
        {
          "en": "A key factor in achieving sustainable development is controlling the level of wouldhavemoved.",
          "tr": "Sürdürülebilir kalkınmayı sağlamada temel faktör, hareket etmiş olacaktı seviyesinin kontrol edilmesidir.",
          "blanked": "A key factor in achieving sustainable development is controlling the level of ________."
        },
        {
          "en": "The primary objective of this project is to analyze the behavior of wouldhavemoved under pressure.",
          "tr": "Bu projenin temel amacı, basınç altında hareket etmiş olacaktı davranışını analiz etmektir.",
          "blanked": "The primary objective of this project is to analyze the behavior of ________ under pressure."
        }
      ],
      "priority": "Orta Sıklık"
    },
    {
      "word": "subside",
      "en": "The data reveal a strong correlation between carbon emissions and subside.",
      "tr": "alçalmak, hafiflemek (deprem vb.)",
      "synonyms": "",
      "type": "noun",
      "en_tr": "Veriler, karbon emisyonları ile alçalmak, hafiflemek (deprem vb.) arasında güçlü bir korelasyon olduğunu ortaya koyuyor.",
      "collocation": "crucial subside, study of subside",
      "sentences": [
        {
          "en": "The data reveal a strong correlation between carbon emissions and subside.",
          "tr": "Veriler, karbon emisyonları ile alçalmak, hafiflemek (deprem vb.) arasında güçlü bir korelasyon olduğunu ortaya koyuyor.",
          "blanked": "The data reveal a strong correlation between carbon emissions and ________."
        },
        {
          "en": "Recent studies have demonstrated the significant impact of subside on the ecosystem.",
          "tr": "Son çalışmalar, alçalmak, hafiflemek (deprem vb.) yapısının ekosistem üzerindeki önemli etkisini göstermiştir.",
          "blanked": "Recent studies have demonstrated the significant impact of ________ on the ecosystem."
        },
        {
          "en": "Researchers must carefully monitor the changes in subside during the experiment.",
          "tr": "Araştırmacılar, deney sırasında alçalmak, hafiflemek (deprem vb.) durumundaki değişimleri dikkatle gözlemlemelidir.",
          "blanked": "Researchers must carefully monitor the changes in ________ during the experiment."
        },
        {
          "en": "A key factor in achieving sustainable development is controlling the level of subside.",
          "tr": "Sürdürülebilir kalkınmayı sağlamada temel faktör, alçalmak, hafiflemek (deprem vb.) seviyesinin kontrol edilmesidir.",
          "blanked": "A key factor in achieving sustainable development is controlling the level of ________."
        },
        {
          "en": "The primary objective of this project is to analyze the behavior of subside under pressure.",
          "tr": "Bu projenin temel amacı, basınç altında alçalmak, hafiflemek (deprem vb.) davranışını analiz etmektir.",
          "blanked": "The primary objective of this project is to analyze the behavior of ________ under pressure."
        }
      ],
      "priority": "Orta Sıklık"
    },
    {
      "word": "loss",
      "en": "The data reveal a strong correlation between carbon emissions and loss.",
      "tr": "önleyecektir.",
      "synonyms": "",
      "type": "noun",
      "en_tr": "Veriler, karbon emisyonları ile önleyecektir arasında güçlü bir korelasyon olduğunu ortaya koyuyor.",
      "collocation": "crucial loss, study of loss",
      "sentences": [
        {
          "en": "The data reveal a strong correlation between carbon emissions and loss.",
          "tr": "Veriler, karbon emisyonları ile önleyecektir arasında güçlü bir korelasyon olduğunu ortaya koyuyor.",
          "blanked": "The data reveal a strong correlation between carbon emissions and ________."
        },
        {
          "en": "Recent studies have demonstrated the significant impact of loss on the ecosystem.",
          "tr": "Son çalışmalar, önleyecektir yapısının ekosistem üzerindeki önemli etkisini göstermiştir.",
          "blanked": "Recent studies have demonstrated the significant impact of ________ on the ecosystem."
        },
        {
          "en": "Researchers must carefully monitor the changes in loss during the experiment.",
          "tr": "Araştırmacılar, deney sırasında önleyecektir durumundaki değişimleri dikkatle gözlemlemelidir.",
          "blanked": "Researchers must carefully monitor the changes in ________ during the experiment."
        },
        {
          "en": "A key factor in achieving sustainable development is controlling the level of loss.",
          "tr": "Sürdürülebilir kalkınmayı sağlamada temel faktör, önleyecektir seviyesinin kontrol edilmesidir.",
          "blanked": "A key factor in achieving sustainable development is controlling the level of ________."
        },
        {
          "en": "The primary objective of this project is to analyze the behavior of loss under pressure.",
          "tr": "Bu projenin temel amacı, basınç altında önleyecektir davranışını analiz etmektir.",
          "blanked": "The primary objective of this project is to analyze the behavior of ________ under pressure."
        }
      ],
      "priority": "Çok Yüksek Sıklık"
    },
    {
      "word": "martian",
      "en": "The data reveal a strong correlation between carbon emissions and martian.",
      "tr": "marslı",
      "synonyms": "",
      "type": "noun",
      "en_tr": "Veriler, karbon emisyonları ile marslı arasında güçlü bir korelasyon olduğunu ortaya koyuyor.",
      "collocation": "crucial martian, study of martian",
      "sentences": [
        {
          "en": "The data reveal a strong correlation between carbon emissions and martian.",
          "tr": "Veriler, karbon emisyonları ile marslı arasında güçlü bir korelasyon olduğunu ortaya koyuyor.",
          "blanked": "The data reveal a strong correlation between carbon emissions and ________."
        },
        {
          "en": "Recent studies have demonstrated the significant impact of martian on the ecosystem.",
          "tr": "Son çalışmalar, marslı yapısının ekosistem üzerindeki önemli etkisini göstermiştir.",
          "blanked": "Recent studies have demonstrated the significant impact of ________ on the ecosystem."
        },
        {
          "en": "Researchers must carefully monitor the changes in martian during the experiment.",
          "tr": "Araştırmacılar, deney sırasında marslı durumundaki değişimleri dikkatle gözlemlemelidir.",
          "blanked": "Researchers must carefully monitor the changes in ________ during the experiment."
        },
        {
          "en": "A key factor in achieving sustainable development is controlling the level of martian.",
          "tr": "Sürdürülebilir kalkınmayı sağlamada temel faktör, marslı seviyesinin kontrol edilmesidir.",
          "blanked": "A key factor in achieving sustainable development is controlling the level of ________."
        },
        {
          "en": "The primary objective of this project is to analyze the behavior of martian under pressure.",
          "tr": "Bu projenin temel amacı, basınç altında marslı davranışını analiz etmektir.",
          "blanked": "The primary objective of this project is to analyze the behavior of ________ under pressure."
        }
      ],
      "priority": "Çok Yüksek Sıklık"
    },
    {
      "word": "inertia",
      "en": "The data reveal a strong correlation between carbon emissions and inertia.",
      "tr": "eylemsizlik, atalet",
      "synonyms": "",
      "type": "noun",
      "en_tr": "Veriler, karbon emisyonları ile eylemsizlik, atalet arasında güçlü bir korelasyon olduğunu ortaya koyuyor.",
      "collocation": "crucial inertia, study of inertia",
      "sentences": [
        {
          "en": "The data reveal a strong correlation between carbon emissions and inertia.",
          "tr": "Veriler, karbon emisyonları ile eylemsizlik, atalet arasında güçlü bir korelasyon olduğunu ortaya koyuyor.",
          "blanked": "The data reveal a strong correlation between carbon emissions and ________."
        },
        {
          "en": "Recent studies have demonstrated the significant impact of inertia on the ecosystem.",
          "tr": "Son çalışmalar, eylemsizlik, atalet yapısının ekosistem üzerindeki önemli etkisini göstermiştir.",
          "blanked": "Recent studies have demonstrated the significant impact of ________ on the ecosystem."
        },
        {
          "en": "Researchers must carefully monitor the changes in inertia during the experiment.",
          "tr": "Araştırmacılar, deney sırasında eylemsizlik, atalet durumundaki değişimleri dikkatle gözlemlemelidir.",
          "blanked": "Researchers must carefully monitor the changes in ________ during the experiment."
        },
        {
          "en": "A key factor in achieving sustainable development is controlling the level of inertia.",
          "tr": "Sürdürülebilir kalkınmayı sağlamada temel faktör, eylemsizlik, atalet seviyesinin kontrol edilmesidir.",
          "blanked": "A key factor in achieving sustainable development is controlling the level of ________."
        },
        {
          "en": "The primary objective of this project is to analyze the behavior of inertia under pressure.",
          "tr": "Bu projenin temel amacı, basınç altında eylemsizlik, atalet davranışını analiz etmektir.",
          "blanked": "The primary objective of this project is to analyze the behavior of ________ under pressure."
        }
      ],
      "priority": "Orta Sıklık"
    },
    {
      "word": "stimulus",
      "en": "The data reveal a strong correlation between carbon emissions and stimulus.",
      "tr": "uyarıcı, dürtü",
      "synonyms": "",
      "type": "noun",
      "en_tr": "Veriler, karbon emisyonları ile uyarıcı, dürtü arasında güçlü bir korelasyon olduğunu ortaya koyuyor.",
      "collocation": "crucial stimulus, study of stimulus",
      "sentences": [
        {
          "en": "The data reveal a strong correlation between carbon emissions and stimulus.",
          "tr": "Veriler, karbon emisyonları ile uyarıcı, dürtü arasında güçlü bir korelasyon olduğunu ortaya koyuyor.",
          "blanked": "The data reveal a strong correlation between carbon emissions and ________."
        },
        {
          "en": "Recent studies have demonstrated the significant impact of stimulus on the ecosystem.",
          "tr": "Son çalışmalar, uyarıcı, dürtü yapısının ekosistem üzerindeki önemli etkisini göstermiştir.",
          "blanked": "Recent studies have demonstrated the significant impact of ________ on the ecosystem."
        },
        {
          "en": "Researchers must carefully monitor the changes in stimulus during the experiment.",
          "tr": "Araştırmacılar, deney sırasında uyarıcı, dürtü durumundaki değişimleri dikkatle gözlemlemelidir.",
          "blanked": "Researchers must carefully monitor the changes in ________ during the experiment."
        },
        {
          "en": "A key factor in achieving sustainable development is controlling the level of stimulus.",
          "tr": "Sürdürülebilir kalkınmayı sağlamada temel faktör, uyarıcı, dürtü seviyesinin kontrol edilmesidir.",
          "blanked": "A key factor in achieving sustainable development is controlling the level of ________."
        },
        {
          "en": "The primary objective of this project is to analyze the behavior of stimulus under pressure.",
          "tr": "Bu projenin temel amacı, basınç altında uyarıcı, dürtü davranışını analiz etmektir.",
          "blanked": "The primary objective of this project is to analyze the behavior of ________ under pressure."
        }
      ],
      "priority": "Orta Sıklık"
    },
    {
      "word": "tolerance",
      "en": "The data reveal a strong correlation between carbon emissions and tolerance.",
      "tr": "tolerans, hoşgörü",
      "synonyms": "",
      "type": "noun",
      "en_tr": "Veriler, karbon emisyonları ile tolerans, hoşgörü arasında güçlü bir korelasyon olduğunu ortaya koyuyor.",
      "collocation": "crucial tolerance, study of tolerance",
      "sentences": [
        {
          "en": "The data reveal a strong correlation between carbon emissions and tolerance.",
          "tr": "Veriler, karbon emisyonları ile tolerans, hoşgörü arasında güçlü bir korelasyon olduğunu ortaya koyuyor.",
          "blanked": "The data reveal a strong correlation between carbon emissions and ________."
        },
        {
          "en": "Recent studies have demonstrated the significant impact of tolerance on the ecosystem.",
          "tr": "Son çalışmalar, tolerans, hoşgörü yapısının ekosistem üzerindeki önemli etkisini göstermiştir.",
          "blanked": "Recent studies have demonstrated the significant impact of ________ on the ecosystem."
        },
        {
          "en": "Researchers must carefully monitor the changes in tolerance during the experiment.",
          "tr": "Araştırmacılar, deney sırasında tolerans, hoşgörü durumundaki değişimleri dikkatle gözlemlemelidir.",
          "blanked": "Researchers must carefully monitor the changes in ________ during the experiment."
        },
        {
          "en": "A key factor in achieving sustainable development is controlling the level of tolerance.",
          "tr": "Sürdürülebilir kalkınmayı sağlamada temel faktör, tolerans, hoşgörü seviyesinin kontrol edilmesidir.",
          "blanked": "A key factor in achieving sustainable development is controlling the level of ________."
        },
        {
          "en": "The primary objective of this project is to analyze the behavior of tolerance under pressure.",
          "tr": "Bu projenin temel amacı, basınç altında tolerans, hoşgörü davranışını analiz etmektir.",
          "blanked": "The primary objective of this project is to analyze the behavior of ________ under pressure."
        }
      ],
      "priority": "Yüksek Sıklık"
    },
    {
      "word": "rational",
      "en": "The data reveal a strong correlation between carbon emissions and rational.",
      "tr": "rasyonel",
      "synonyms": "",
      "type": "noun",
      "en_tr": "Veriler, karbon emisyonları ile rasyonel arasında güçlü bir korelasyon olduğunu ortaya koyuyor.",
      "collocation": "crucial rational, study of rational",
      "sentences": [
        {
          "en": "The data reveal a strong correlation between carbon emissions and rational.",
          "tr": "Veriler, karbon emisyonları ile rasyonel arasında güçlü bir korelasyon olduğunu ortaya koyuyor.",
          "blanked": "The data reveal a strong correlation between carbon emissions and ________."
        },
        {
          "en": "Recent studies have demonstrated the significant impact of rational on the ecosystem.",
          "tr": "Son çalışmalar, rasyonel yapısının ekosistem üzerindeki önemli etkisini göstermiştir.",
          "blanked": "Recent studies have demonstrated the significant impact of ________ on the ecosystem."
        },
        {
          "en": "Researchers must carefully monitor the changes in rational during the experiment.",
          "tr": "Araştırmacılar, deney sırasında rasyonel durumundaki değişimleri dikkatle gözlemlemelidir.",
          "blanked": "Researchers must carefully monitor the changes in ________ during the experiment."
        },
        {
          "en": "A key factor in achieving sustainable development is controlling the level of rational.",
          "tr": "Sürdürülebilir kalkınmayı sağlamada temel faktör, rasyonel seviyesinin kontrol edilmesidir.",
          "blanked": "A key factor in achieving sustainable development is controlling the level of ________."
        },
        {
          "en": "The primary objective of this project is to analyze the behavior of rational under pressure.",
          "tr": "Bu projenin temel amacı, basınç altında rasyonel davranışını analiz etmektir.",
          "blanked": "The primary objective of this project is to analyze the behavior of ________ under pressure."
        }
      ],
      "priority": "Çok Yüksek Sıklık"
    },
    {
      "word": "similarto",
      "en": "The data reveal a strong correlation between carbon emissions and similarto.",
      "tr": "-e benzer",
      "synonyms": "",
      "type": "noun",
      "en_tr": "Veriler, karbon emisyonları ile -e benzer arasında güçlü bir korelasyon olduğunu ortaya koyuyor.",
      "collocation": "crucial similarto, study of similarto",
      "sentences": [
        {
          "en": "The data reveal a strong correlation between carbon emissions and similarto.",
          "tr": "Veriler, karbon emisyonları ile -e benzer arasında güçlü bir korelasyon olduğunu ortaya koyuyor.",
          "blanked": "The data reveal a strong correlation between carbon emissions and ________."
        },
        {
          "en": "Recent studies have demonstrated the significant impact of similarto on the ecosystem.",
          "tr": "Son çalışmalar, -e benzer yapısının ekosistem üzerindeki önemli etkisini göstermiştir.",
          "blanked": "Recent studies have demonstrated the significant impact of ________ on the ecosystem."
        },
        {
          "en": "Researchers must carefully monitor the changes in similarto during the experiment.",
          "tr": "Araştırmacılar, deney sırasında -e benzer durumundaki değişimleri dikkatle gözlemlemelidir.",
          "blanked": "Researchers must carefully monitor the changes in ________ during the experiment."
        },
        {
          "en": "A key factor in achieving sustainable development is controlling the level of similarto.",
          "tr": "Sürdürülebilir kalkınmayı sağlamada temel faktör, -e benzer seviyesinin kontrol edilmesidir.",
          "blanked": "A key factor in achieving sustainable development is controlling the level of ________."
        },
        {
          "en": "The primary objective of this project is to analyze the behavior of similarto under pressure.",
          "tr": "Bu projenin temel amacı, basınç altında -e benzer davranışını analiz etmektir.",
          "blanked": "The primary objective of this project is to analyze the behavior of ________ under pressure."
        }
      ],
      "priority": "Orta Sıklık"
    },
    {
      "word": "disease",
      "en": "The data reveal a strong correlation between carbon emissions and disease.",
      "tr": "hastalık",
      "synonyms": "",
      "type": "noun",
      "en_tr": "Veriler, karbon emisyonları ile hastalık arasında güçlü bir korelasyon olduğunu ortaya koyuyor.",
      "collocation": "crucial disease, study of disease",
      "sentences": [
        {
          "en": "The data reveal a strong correlation between carbon emissions and disease.",
          "tr": "Veriler, karbon emisyonları ile hastalık arasında güçlü bir korelasyon olduğunu ortaya koyuyor.",
          "blanked": "The data reveal a strong correlation between carbon emissions and ________."
        },
        {
          "en": "Recent studies have demonstrated the significant impact of disease on the ecosystem.",
          "tr": "Son çalışmalar, hastalık yapısının ekosistem üzerindeki önemli etkisini göstermiştir.",
          "blanked": "Recent studies have demonstrated the significant impact of ________ on the ecosystem."
        },
        {
          "en": "Researchers must carefully monitor the changes in disease during the experiment.",
          "tr": "Araştırmacılar, deney sırasında hastalık durumundaki değişimleri dikkatle gözlemlemelidir.",
          "blanked": "Researchers must carefully monitor the changes in ________ during the experiment."
        },
        {
          "en": "A key factor in achieving sustainable development is controlling the level of disease.",
          "tr": "Sürdürülebilir kalkınmayı sağlamada temel faktör, hastalık seviyesinin kontrol edilmesidir.",
          "blanked": "A key factor in achieving sustainable development is controlling the level of ________."
        },
        {
          "en": "The primary objective of this project is to analyze the behavior of disease under pressure.",
          "tr": "Bu projenin temel amacı, basınç altında hastalık davranışını analiz etmektir.",
          "blanked": "The primary objective of this project is to analyze the behavior of ________ under pressure."
        }
      ],
      "priority": "Çok Yüksek Sıklık"
    },
    {
      "word": "resources",
      "en": "The data reveal a strong correlation between carbon emissions and resources.",
      "tr": "kaynaklar",
      "synonyms": "",
      "type": "noun",
      "en_tr": "Veriler, karbon emisyonları ile kaynaklar arasında güçlü bir korelasyon olduğunu ortaya koyuyor.",
      "collocation": "crucial resources, study of resources",
      "sentences": [
        {
          "en": "The data reveal a strong correlation between carbon emissions and resources.",
          "tr": "Veriler, karbon emisyonları ile kaynaklar arasında güçlü bir korelasyon olduğunu ortaya koyuyor.",
          "blanked": "The data reveal a strong correlation between carbon emissions and ________."
        },
        {
          "en": "Recent studies have demonstrated the significant impact of resources on the ecosystem.",
          "tr": "Son çalışmalar, kaynaklar yapısının ekosistem üzerindeki önemli etkisini göstermiştir.",
          "blanked": "Recent studies have demonstrated the significant impact of ________ on the ecosystem."
        },
        {
          "en": "Researchers must carefully monitor the changes in resources during the experiment.",
          "tr": "Araştırmacılar, deney sırasında kaynaklar durumundaki değişimleri dikkatle gözlemlemelidir.",
          "blanked": "Researchers must carefully monitor the changes in ________ during the experiment."
        },
        {
          "en": "A key factor in achieving sustainable development is controlling the level of resources.",
          "tr": "Sürdürülebilir kalkınmayı sağlamada temel faktör, kaynaklar seviyesinin kontrol edilmesidir.",
          "blanked": "A key factor in achieving sustainable development is controlling the level of ________."
        },
        {
          "en": "The primary objective of this project is to analyze the behavior of resources under pressure.",
          "tr": "Bu projenin temel amacı, basınç altında kaynaklar davranışını analiz etmektir.",
          "blanked": "The primary objective of this project is to analyze the behavior of ________ under pressure."
        }
      ],
      "priority": "Çok Yüksek Sıklık"
    },
    {
      "word": "social",
      "en": "The data reveal a strong correlation between carbon emissions and social.",
      "tr": "sosyal-duygusal",
      "synonyms": "",
      "type": "noun",
      "en_tr": "Veriler, karbon emisyonları ile sosyal-duygusal arasında güçlü bir korelasyon olduğunu ortaya koyuyor.",
      "collocation": "crucial social, study of social",
      "sentences": [
        {
          "en": "The data reveal a strong correlation between carbon emissions and social.",
          "tr": "Veriler, karbon emisyonları ile sosyal-duygusal arasında güçlü bir korelasyon olduğunu ortaya koyuyor.",
          "blanked": "The data reveal a strong correlation between carbon emissions and ________."
        },
        {
          "en": "Recent studies have demonstrated the significant impact of social on the ecosystem.",
          "tr": "Son çalışmalar, sosyal-duygusal yapısının ekosistem üzerindeki önemli etkisini göstermiştir.",
          "blanked": "Recent studies have demonstrated the significant impact of ________ on the ecosystem."
        },
        {
          "en": "Researchers must carefully monitor the changes in social during the experiment.",
          "tr": "Araştırmacılar, deney sırasında sosyal-duygusal durumundaki değişimleri dikkatle gözlemlemelidir.",
          "blanked": "Researchers must carefully monitor the changes in ________ during the experiment."
        },
        {
          "en": "A key factor in achieving sustainable development is controlling the level of social.",
          "tr": "Sürdürülebilir kalkınmayı sağlamada temel faktör, sosyal-duygusal seviyesinin kontrol edilmesidir.",
          "blanked": "A key factor in achieving sustainable development is controlling the level of ________."
        },
        {
          "en": "The primary objective of this project is to analyze the behavior of social under pressure.",
          "tr": "Bu projenin temel amacı, basınç altında sosyal-duygusal davranışını analiz etmektir.",
          "blanked": "The primary objective of this project is to analyze the behavior of ________ under pressure."
        }
      ],
      "priority": "Çok Yüksek Sıklık"
    },
    {
      "word": "odd",
      "en": "The data reveal a strong correlation between carbon emissions and odd.",
      "tr": "tuhaf, tek sayı",
      "synonyms": "",
      "type": "noun",
      "en_tr": "Veriler, karbon emisyonları ile tuhaf, tek sayı arasında güçlü bir korelasyon olduğunu ortaya koyuyor.",
      "collocation": "crucial odd, study of odd",
      "sentences": [
        {
          "en": "The data reveal a strong correlation between carbon emissions and odd.",
          "tr": "Veriler, karbon emisyonları ile tuhaf, tek sayı arasında güçlü bir korelasyon olduğunu ortaya koyuyor.",
          "blanked": "The data reveal a strong correlation between carbon emissions and ________."
        },
        {
          "en": "Recent studies have demonstrated the significant impact of odd on the ecosystem.",
          "tr": "Son çalışmalar, tuhaf, tek sayı yapısının ekosistem üzerindeki önemli etkisini göstermiştir.",
          "blanked": "Recent studies have demonstrated the significant impact of ________ on the ecosystem."
        },
        {
          "en": "Researchers must carefully monitor the changes in odd during the experiment.",
          "tr": "Araştırmacılar, deney sırasında tuhaf, tek sayı durumundaki değişimleri dikkatle gözlemlemelidir.",
          "blanked": "Researchers must carefully monitor the changes in ________ during the experiment."
        },
        {
          "en": "A key factor in achieving sustainable development is controlling the level of odd.",
          "tr": "Sürdürülebilir kalkınmayı sağlamada temel faktör, tuhaf, tek sayı seviyesinin kontrol edilmesidir.",
          "blanked": "A key factor in achieving sustainable development is controlling the level of ________."
        },
        {
          "en": "The primary objective of this project is to analyze the behavior of odd under pressure.",
          "tr": "Bu projenin temel amacı, basınç altında tuhaf, tek sayı davranışını analiz etmektir.",
          "blanked": "The primary objective of this project is to analyze the behavior of ________ under pressure."
        }
      ],
      "priority": "Orta Sıklık"
    },
    {
      "word": "vary",
      "en": "It is essential to vary the system properties to get accurate results.",
      "tr": "çeşitlilik göstermek, değişmek",
      "synonyms": "",
      "type": "noun",
      "en_tr": "Doğru sonuçlar elde etmek için sistem özelliklerini çeşitlilik göstermek, değişmek gereklidir.",
      "collocation": "crucial vary, study of vary",
      "sentences": [
        {
          "en": "It is essential to vary the system properties to get accurate results.",
          "tr": "Doğru sonuçlar elde etmek için sistem özelliklerini çeşitlilik göstermek, değişmek gereklidir.",
          "blanked": "It is essential to ________ the system properties to get accurate results."
        },
        {
          "en": "Researchers always seek to vary new methodologies in this field.",
          "tr": "Araştırmacılar bu alanda her zaman yeni metodolojiler çeşitlilik göstermek, değişmek isterler.",
          "blanked": "Researchers always seek to ________ new methodologies in this field."
        },
        {
          "en": "We need to vary the main factors before drawing a final conclusion.",
          "tr": "Nihai bir sonuca varmadan önce ana faktörleri çeşitlilik göstermek, değişmek gerekir.",
          "blanked": "We need to ________ the main factors before drawing a final conclusion."
        },
        {
          "en": "Several parameters were designed to vary the chemical reaction.",
          "tr": "Kimyasal reaksiyonu çeşitlilik göstermek, değişmek için birkaç parametre tasarlandı.",
          "blanked": "Several parameters were designed to ________ the chemical reaction."
        },
        {
          "en": "The new algorithm can vary the overall processing speed.",
          "tr": "Yeni algoritma, genel işlem hızını çeşitlilik göstermek, değişmek konusunda yardımcı olabilir.",
          "blanked": "The new algorithm can ________ the overall processing speed."
        }
      ],
      "priority": "Çok Yüksek Sıklık"
    },
    {
      "word": "combine",
      "en": "It is essential to combine the system properties to get accurate results.",
      "tr": "birleşmek, bir araya getirmek",
      "synonyms": "",
      "type": "noun",
      "en_tr": "Doğru sonuçlar elde etmek için sistem özelliklerini birleşmek, bir araya getirmek gereklidir.",
      "collocation": "crucial combine, study of combine",
      "sentences": [
        {
          "en": "It is essential to combine the system properties to get accurate results.",
          "tr": "Doğru sonuçlar elde etmek için sistem özelliklerini birleşmek, bir araya getirmek gereklidir.",
          "blanked": "It is essential to ________ the system properties to get accurate results."
        },
        {
          "en": "Researchers always seek to combine new methodologies in this field.",
          "tr": "Araştırmacılar bu alanda her zaman yeni metodolojiler birleşmek, bir araya getirmek isterler.",
          "blanked": "Researchers always seek to ________ new methodologies in this field."
        },
        {
          "en": "We need to combine the main factors before drawing a final conclusion.",
          "tr": "Nihai bir sonuca varmadan önce ana faktörleri birleşmek, bir araya getirmek gerekir.",
          "blanked": "We need to ________ the main factors before drawing a final conclusion."
        },
        {
          "en": "Several parameters were designed to combine the chemical reaction.",
          "tr": "Kimyasal reaksiyonu birleşmek, bir araya getirmek için birkaç parametre tasarlandı.",
          "blanked": "Several parameters were designed to ________ the chemical reaction."
        },
        {
          "en": "The new algorithm can combine the overall processing speed.",
          "tr": "Yeni algoritma, genel işlem hızını birleşmek, bir araya getirmek konusunda yardımcı olabilir.",
          "blanked": "The new algorithm can ________ the overall processing speed."
        }
      ],
      "priority": "Yüksek Sıklık"
    },
    {
      "word": "havetolearnbecome",
      "en": "It is essential to havetolearnbecome the system properties to get accurate results.",
      "tr": "öğrenmek ve olmak zorunda olmak",
      "synonyms": "",
      "type": "noun",
      "en_tr": "Doğru sonuçlar elde etmek için sistem özelliklerini öğrenmek ve olmak zorunda olmak gereklidir.",
      "collocation": "crucial havetolearnbecome, study of havetolearnbecome",
      "sentences": [
        {
          "en": "It is essential to havetolearnbecome the system properties to get accurate results.",
          "tr": "Doğru sonuçlar elde etmek için sistem özelliklerini öğrenmek ve olmak zorunda olmak gereklidir.",
          "blanked": "It is essential to ________ the system properties to get accurate results."
        },
        {
          "en": "Researchers always seek to havetolearnbecome new methodologies in this field.",
          "tr": "Araştırmacılar bu alanda her zaman yeni metodolojiler öğrenmek ve olmak zorunda olmak isterler.",
          "blanked": "Researchers always seek to ________ new methodologies in this field."
        },
        {
          "en": "We need to havetolearnbecome the main factors before drawing a final conclusion.",
          "tr": "Nihai bir sonuca varmadan önce ana faktörleri öğrenmek ve olmak zorunda olmak gerekir.",
          "blanked": "We need to ________ the main factors before drawing a final conclusion."
        },
        {
          "en": "Several parameters were designed to havetolearnbecome the chemical reaction.",
          "tr": "Kimyasal reaksiyonu öğrenmek ve olmak zorunda olmak için birkaç parametre tasarlandı.",
          "blanked": "Several parameters were designed to ________ the chemical reaction."
        },
        {
          "en": "The new algorithm can havetolearnbecome the overall processing speed.",
          "tr": "Yeni algoritma, genel işlem hızını öğrenmek ve olmak zorunda olmak konusunda yardımcı olabilir.",
          "blanked": "The new algorithm can ________ the overall processing speed."
        }
      ],
      "priority": "Orta Sıklık"
    },
    {
      "word": "surface",
      "en": "It is essential to surface the system properties to get accurate results.",
      "tr": "yüzey, açığa çıkmak",
      "synonyms": "",
      "type": "noun",
      "en_tr": "Doğru sonuçlar elde etmek için sistem özelliklerini yüzey, açığa çıkmak gereklidir.",
      "collocation": "crucial surface, study of surface",
      "sentences": [
        {
          "en": "It is essential to surface the system properties to get accurate results.",
          "tr": "Doğru sonuçlar elde etmek için sistem özelliklerini yüzey, açığa çıkmak gereklidir.",
          "blanked": "It is essential to ________ the system properties to get accurate results."
        },
        {
          "en": "Researchers always seek to surface new methodologies in this field.",
          "tr": "Araştırmacılar bu alanda her zaman yeni metodolojiler yüzey, açığa çıkmak isterler.",
          "blanked": "Researchers always seek to ________ new methodologies in this field."
        },
        {
          "en": "We need to surface the main factors before drawing a final conclusion.",
          "tr": "Nihai bir sonuca varmadan önce ana faktörleri yüzey, açığa çıkmak gerekir.",
          "blanked": "We need to ________ the main factors before drawing a final conclusion."
        },
        {
          "en": "Several parameters were designed to surface the chemical reaction.",
          "tr": "Kimyasal reaksiyonu yüzey, açığa çıkmak için birkaç parametre tasarlandı.",
          "blanked": "Several parameters were designed to ________ the chemical reaction."
        },
        {
          "en": "The new algorithm can surface the overall processing speed.",
          "tr": "Yeni algoritma, genel işlem hızını yüzey, açığa çıkmak konusunda yardımcı olabilir.",
          "blanked": "The new algorithm can ________ the overall processing speed."
        }
      ],
      "priority": "Çok Yüksek Sıklık"
    }
  ]
}